pystructures/linked_lists.py
pystructures/__init__.py
pystructures-0.0.4.dist-info/DESCRIPTION.rst
pystructures-0.0.4.dist-info/WHEEL
pystructures-0.0.4.dist-info/METADATA
pystructures-0.0.4.dist-info/RECORD
pystructures-0.0.4.dist-info/top_level.txt
pystructures-0.0.4.dist-info/metadata.json
