Metadata-Version: 2.0
Name: pystructures
Version: 0.0.4
Summary: Data Structures made simple
Home-page: http://github.com/apranav19/pystructures
Author: Pranav Angara
Author-email: apranav19@gmail.com
License: MIT
Platform: UNKNOWN
Requires-Dist: future
